<?xml version="1.0" ?>
<page layout="1column" xmlns:xsi="http://www.w3.org/2001/XMLSchema-instance" xsi:noNamespaceSchemaLocation="urn:magento:framework:View/Layout/etc/page_configuration.xsd">
	<body>
		<referenceContainer name="content">
			<block class="SM\DigitalProduct\Block\Bpjs\Index" name="bpjs.index" template="SM_DigitalProduct::bpjs.phtml">
                <block class="SM\DigitalProduct\Block\Banner" name="digitalproduct.banner" template="SM_DigitalProduct::index/banner.phtml"/>
                <block class="SM\DigitalProduct\Block\Tab" name="digitalproduct.tab" template="SM_DigitalProduct::index/tab.phtml"/>
            </block>
		</referenceContainer>
	</body>
</page>
